{
  "version": "7",
  "dialect": "postgresql",
  "entries": [
    {
      "idx": 0,
      "version": "7",
      "when": 1733510445145,
      "tag": "0000_thankful_killmonger",
      "breakpoints": true
    },
    {
      "idx": 1,
      "version": "7",
      "when": 1733510715497,
      "tag": "0001_kind_proteus",
      "breakpoints": true
    },
    {
      "idx": 2,
      "version": "7",
      "when": 1733610609002,
      "tag": "0002_wandering_celestials",
      "breakpoints": true
    },
    {
      "idx": 3,
      "version": "7",
      "when": 1733610702596,
      "tag": "0003_odd_lord_hawal",
      "breakpoints": true
    },
    {
      "idx": 4,
      "version": "7",
      "when": 1733699979108,
      "tag": "0004_worthless_forgotten_one",
      "breakpoints": true
    }
  ]
}